auto_pahe.py
config.py
kwikdown.py
ap_core/__init__.py
ap_core/banners.py
ap_core/browser.py
ap_core/cache.py
ap_core/config.py
ap_core/fuzzy_search.py
ap_core/notifications.py
ap_core/parser.py
ap_core/platform_paths.py
ap_core/resume_manager.py
collection/__init__.py
collection/commands.py
collection/manager.py
collection/models.py
collection/stats.py
features/__init__.py
features/manager.py
features/pahesort.py
autopahe-3.5.1.dist-info/METADATA
autopahe-3.5.1.dist-info/WHEEL
autopahe-3.5.1.dist-info/entry_points.txt
autopahe-3.5.1.dist-info/top_level.txt
autopahe-3.5.1.dist-info/RECORD
