Metadata-Version: 2.4
Name: autopahe
Version: 3.5.1
Summary: Cross-platform anime downloader for AnimePahe with advanced features: smart caching, cross-platform streaming, notifications, filters, batch downloads, and record management
Author-email: haxsys <haxsysgit@users.noreply.github.com>
License: MIT License
Project-URL: Homepage, https://github.com/haxsysgit/autopahe
Project-URL: Repository, https://github.com/haxsysgit/autopahe
Project-URL: Issues, https://github.com/haxsysgit/autopahe/issues
Keywords: anime,downloader,animepahe,automation,cli
Classifier: Development Status :: 4 - Beta
Classifier: Environment :: Console
Classifier: Intended Audience :: End Users/Desktop
Classifier: License :: OSI Approved :: MIT License
Classifier: Operating System :: OS Independent
Classifier: Programming Language :: Python :: 3
Classifier: Programming Language :: Python :: 3.8
Classifier: Programming Language :: Python :: 3.9
Classifier: Programming Language :: Python :: 3.10
Classifier: Programming Language :: Python :: 3.11
Classifier: Programming Language :: Python :: 3.12
Classifier: Topic :: Multimedia :: Video
Requires-Python: >=3.8
Requires-Dist: requests>=2.31.0
Requires-Dist: playwright>=1.45.0
Requires-Dist: tqdm>=4.66.0
Requires-Dist: colorama>=0.4.6
Requires-Dist: rich>=13.0.0
Requires-Dist: beautifulsoup4>=4.12.0
Provides-Extra: test
Requires-Dist: pytest>=7.0; extra == "test"
Provides-Extra: publish
Requires-Dist: build>=1.2.0; extra == "publish"
Requires-Dist: twine>=4.0.2; extra == "publish"
